my_sin_api/__init__.py
my_sin_api/_base.py
my_sin_api/_models.py
my_sin_api/sin_api.py
sinAPI-0.2.6.dist-info/METADATA
sinAPI-0.2.6.dist-info/WHEEL
sinAPI-0.2.6.dist-info/top_level.txt
sinAPI-0.2.6.dist-info/RECORD
