Metadata-Version: 2.1
Name: sinAPI
Version: 0.2.6
Summary: Интерфейс связи ботов Tegtory с апи
Author-email: sinortax <github@sinortax.ru>
License: MIT License
Project-URL: Repository, https://github.com/sheptalo/my_sin_api
Classifier: Development Status :: 5 - Production/Stable
Classifier: Programming Language :: Python :: 3
Classifier: License :: OSI Approved :: MIT License
Classifier: Operating System :: OS Independent
Requires-Python: >=3.8
Requires-Dist: requests>=2.26.0
